led_cube_data/__init__.py
led_cube_data/assembler.py
led_cube_data/parser/__init__.py
led_cube_data/parser/animation.py
led_cube_data/parser/animation_v1.py
led_cube_data/parser/cube_file.py
led_cube_data/parser/frame.py
led_cube_data/parser/frame_v1.py
led_cube_data/parser/library.py
led_cube_data/parser/library_v1.py
led_cube_data/parser/parser.py
led_cube_data/parser/primary_header.py
led_cube_data/serializer.py
led_cube_data-1.1.0.dist-info/LICENSE
led_cube_data-1.1.0.dist-info/WHEEL
led_cube_data-1.1.0.dist-info/METADATA
led_cube_data-1.1.0.dist-info/RECORD
