Metadata-Version: 2.1
Name: led-cube-data
Version: 1.1.0
Summary: File specification used in my LED cube projects.
Home-page: https://github.com/crash8229/led-cube-data
License: GPL-3.0-only
Author: crash8229
Author-email: mu304007@gmail.com
Requires-Python: >=3.10,<4.0
Classifier: Development Status :: 4 - Beta
Classifier: License :: OSI Approved :: GNU General Public License v3 (GPLv3)
Classifier: Programming Language :: Python :: 3
Classifier: Programming Language :: Python :: 3.10
Requires-Dist: PyYAML (>=6.0,<7.0)
Requires-Dist: construct (>=2.10.68,<3.0.0)
Requires-Dist: kaitaistruct (>=0.10,<0.11)
Project-URL: Repository, https://github.com/crash8229/led-cube-data
